alexdataconverter/__init__.py
alexdataconverter/data_converter.py
alexdataconverter-0.11.dist-info/LICENSE
alexdataconverter-0.11.dist-info/METADATA
alexdataconverter-0.11.dist-info/WHEEL
alexdataconverter-0.11.dist-info/top_level.txt
alexdataconverter-0.11.dist-info/RECORD
